amtrak_analysis/__init__.py
amtrak_analysis/data_preprocessing.py
amtrak_analysis/model_evaluation.py
amtrak_analysis/smoothing_methods.py
amtrak_analysis/utils.py
amtrak_analysis/visualization.py
amtrak_analysis/data/Amtrak.csv
tests/__init__.py
tests/test_amtrak_analysis.py
amtrak_analysis-0.6.dist-info/METADATA
amtrak_analysis-0.6.dist-info/WHEEL
amtrak_analysis-0.6.dist-info/top_level.txt
amtrak_analysis-0.6.dist-info/RECORD
